pyckup_core/__init__.py
pyckup_core/call_logging.py
pyckup_core/conversation_config.py
pyckup_core/extractor_test.py
pyckup_core/llm_extractor.py
pyckup_core/pyckup.py
pyckup_core/pyckup_test.py
pyckup_core/softphone.py
pyckup_core/softphone_test.py
pyckup_core/conf/softphone_config.yaml
pyckup_core/resources/processing.wav
samples/__init__.py
samples/sample_conversation.py
samples/sample_trunks.py
pyckup_lib-1.0.7.dist-info/LICENSE
pyckup_lib-1.0.7.dist-info/METADATA
pyckup_lib-1.0.7.dist-info/WHEEL
pyckup_lib-1.0.7.dist-info/top_level.txt
pyckup_lib-1.0.7.dist-info/RECORD
