Metadata-Version: 2.1
Name: pyckup-lib
Version: 1.0.7
License-File: LICENSE
Requires-Dist: langchain-community
Requires-Dist: langchain-core
Requires-Dist: langchain-openai
Requires-Dist: numpy
Requires-Dist: openai
Requires-Dist: pathlib
Requires-Dist: pydantic
Requires-Dist: pydub
Requires-Dist: pyyaml
Requires-Dist: websocket-client
